nomad_camels_driver_PID/PID.py
nomad_camels_driver_PID/PID_config_sub.py
nomad_camels_driver_PID/PID_manual_control.py
nomad_camels_driver_PID/PID_ophyd.py
nomad_camels_driver_pid-0.3.1.dist-info/licenses/LICENSE.txt
nomad_camels_driver_pid-0.3.1.dist-info/METADATA
nomad_camels_driver_pid-0.3.1.dist-info/WHEEL
nomad_camels_driver_pid-0.3.1.dist-info/top_level.txt
nomad_camels_driver_pid-0.3.1.dist-info/RECORD
