Metadata-Version: 2.4
Name: nomad_camels_driver_PID
Version: 0.3.1
Summary: This package provides everything to run a PID Controller with.
Author-email: FAIRmat - HU Berlin <nomad-camels@fau.de>
Project-URL: GitHub Page, https://github.com/FAU-LAP/NOMAD-CAMELS
Project-URL: Documentation, https://fau-lap.github.io/NOMAD-CAMELS/doc/instruments/instruments.html
Classifier: Programming Language :: Python :: 3
Classifier: License :: OSI Approved :: GNU Lesser General Public License v2 (LGPLv2)
Requires-Python: >=3.9.6
License-File: LICENSE.txt
Requires-Dist: simple-pid
Requires-Dist: nomad-camels>=1.8.3
Dynamic: license-file
